local_gemma/__init__.py
local_gemma/attention.py
local_gemma/cli.py
local_gemma/modeling_local_gemma_2.py
local_gemma/utils/__init__.py
local_gemma/utils/benchmark.py
local_gemma/utils/config.py
local_gemma-0.2.0.dist-info/LICENSE
local_gemma-0.2.0.dist-info/METADATA
local_gemma-0.2.0.dist-info/WHEEL
local_gemma-0.2.0.dist-info/entry_points.txt
local_gemma-0.2.0.dist-info/top_level.txt
local_gemma-0.2.0.dist-info/RECORD
